echo_pypi/__init__.py
echo_pypi/cli.py
echo_pypi-0.1.0.dist-info/WHEEL
echo_pypi-0.1.0.dist-info/METADATA
echo_pypi-0.1.0.dist-info/RECORD
